LICENSE
MANIFEST.in
README.md
requirements.txt
setup.py
bcg/__init__.py
bcg/config.py
bcg/gateway.py
bcg/utils.py
bcg.egg-info/PKG-INFO
bcg.egg-info/SOURCES.txt
bcg.egg-info/dependency_links.txt
bcg.egg-info/entry_points.txt
bcg.egg-info/requires.txt
bcg.egg-info/top_level.txt