Metadata-Version: 2.1
Name: bcg
Version: 1.16.2
Summary: BigClown USB Gateway
Home-page: https://github.com/bigclownlabs/bch-usb-gateway
Author: HARDWARIO s.r.o.
Author-email: karel.blavka@bigclown.com
License: MIT
Keywords: BigClown,BigClownLabs,gateway,MQTT
Platform: UNKNOWN
Classifier: Development Status :: 5 - Production/Stable
Classifier: Intended Audience :: Developers
Classifier: License :: OSI Approved :: MIT License
Classifier: Operating System :: OS Independent
Classifier: Natural Language :: English
Classifier: Programming Language :: Python
Classifier: Programming Language :: Python :: 2
Classifier: Programming Language :: Python :: 2.6
Classifier: Programming Language :: Python :: 2.7
Classifier: Programming Language :: Python :: 3
Classifier: Programming Language :: Python :: 3.2
Classifier: Programming Language :: Python :: 3.3
Classifier: Programming Language :: Python :: 3.4
Classifier: Programming Language :: Python :: 3.5
Classifier: Programming Language :: Python :: 3.6
Classifier: Topic :: Communications
Classifier: Topic :: Internet
Classifier: Topic :: Utilities
Classifier: Environment :: Console
